mockee/__init__.py
mockee/__meta__.py
mockee/mockee.py
mockee/resolver.py
mockee-0.4.0.dist-info/LICENSE
mockee-0.4.0.dist-info/METADATA
mockee-0.4.0.dist-info/WHEEL
mockee-0.4.0.dist-info/top_level.txt
mockee-0.4.0.dist-info/RECORD
