Metadata-Version: 2.1
Name: mockee
Version: 0.4.0
Summary: Mock data(JSON) generator for Python3
Home-page: https://gitee.com/hyjiacan/mockee
Author: hyjiacan
Author-email: hyjiacan@163.com
Maintainer: hyjiacan
Maintainer-email: hyjiacan@163.com
License: MIT
Project-URL: Documention, https://gitee.com/hyjiacan/mockee/wikis
Project-URL: Code, https://gitee.com/hyjiacan/mockee
Project-URL: Issue tracker, https://gitee.com/hyjiacan/mockee/issues
Platform: UNKNOWN
Classifier: Development Status :: 3 - Alpha
Classifier: Intended Audience :: Developers
Classifier: License :: OSI Approved :: MIT License
Classifier: Operating System :: OS Independent
Classifier: Programming Language :: Python :: 3
Classifier: Topic :: Internet :: WWW/HTTP :: Dynamic Content
Requires-Python: >=3.5
